metasporeflow/__init__.py
metasporeflow/executors/__init__.py
metasporeflow/executors/flow_executor.py
metasporeflow/executors/local_flow_executor.py
metasporeflow/flows/__init__.py
metasporeflow/flows/flow_loader.py
metasporeflow/flows/metaspore_flow.py
metasporeflow/flows/metaspore_oflline_flow.py
metasporeflow/offline/local_offline_executor.py
metasporeflow/offline/scheduler/__init__.py
metasporeflow/offline/scheduler/offline_crontab_scheduler.py
metasporeflow/offline/scheduler/scheduler.py
metasporeflow/offline/scheduler/scheduler_type.py
metasporeflow/offline/task/__init__.py
metasporeflow/offline/task/offline_python_task.py
metasporeflow/offline/task/task.py
metasporeflow/offline/utils/file_util.py
metasporeflow/online/check_service.py
metasporeflow/online/cloud_consul.py
metasporeflow/online/common.py
metasporeflow/online/compose_config.py
metasporeflow/online/monitor_service.py
metasporeflow/online/online_executor.py
metasporeflow/online/online_flow.py
metasporeflow/online/online_generator.py
metasporeflow/online/service_config.py
metasporeflow/resources/__init__.py
metasporeflow/resources/resource.py
metasporeflow/resources/resource_loader.py
metasporeflow/resources/resource_manager.py
metasporeflow-0.1.3.dist-info/METADATA
metasporeflow-0.1.3.dist-info/WHEEL
metasporeflow-0.1.3.dist-info/top_level.txt
metasporeflow-0.1.3.dist-info/RECORD
